<xml xmlns="http://www.w3.org/1999/xhtml">
  <tab name="init" type="InitTab" active="false" scrollx="891" scrolly="352.5" scale="0.9"></tab>
  <tab name="main" type="MainTab" active="true" scrollx="891" scrolly="352.5" scale="0.9">
    <block xmlns="https://developers.google.com/blockly/xml" type="whenClicked" id="vP7tyY[m6eE5r:TvzaK7" x="-930" y="-290">
      <mutation xmlns="http://www.w3.org/1999/xhtml" enableifmissed="false"></mutation>
      <value name="VALUE">
        <block type="objectList" id="v^*(gDW]aJ1_K7bsqg)C">
          <field name="FIELDNAME">Text</field>
        </block>
      </value>
      <statement name="DO">
        <block type="openWebPage" id="w:w^h]P^+L?v2#BWl=:k">
          <field name="MODE">NEW</field>
          <value name="URL">
            <shadow type="text" id="5`,o?wP%vaQldu,2?nv-">
              <field name="TEXT">https://vimeo.com/3dguima/i-am-batman</field>
            </shadow>
          </value>
        </block>
      </statement>
    </block>
  </tab>
  <editorsettings viewport-x="1116.4000732421873" viewport-y="28" viewport-w="817.587" viewport-h="560.1" viewport-hidden="false" toolbox-library-mode="false" toolbox-minimized-mode="false"></editorsettings>
</xml>